{
    "SBD": "06000007",
    "toan": 6.0,
    "van": 5.75,
    "ngoaiNgu": null,
    "su": null,
    "dia": null,
    "GDKTPL": null,
    "li": null,
    "hoa": 0.25,
    "sinh": null,
    "tin": 3.5,
    "congNghe": null,
    "maNgoaiNgu": null,
    "THMs": [
        {
            "THM": "A00",
            "mon": [
                "toan",
                "ly",
                "hoa"
            ],
            "diem": 12.0
        },
        {
            "THM": "C02",
            "mon": [
                "van",
                "toan",
                "hoa"
            ],
            "diem": 12.0
        }
    ]
}