{
    "SBD": "42000004",
    "toan": 4.25,
    "van": 9.25,
    "ngoaiNgu": null,
    "su": null,
    "dia": null,
    "GDKTPL": null,
    "li": null,
    "hoa": 9.0,
    "sinh": 5.75,
    "tin": null,
    "congNghe": null,
    "maNgoaiNgu": null,
    "THMs": [
        {
            "THM": "A00",
            "mon": [
                "toan",
                "ly",
                "hoa"
            ],
            "diem": 22.5
        },
        {
            "THM": "B00",
            "mon": [
                "toan",
                "hoa",
                "sinh"
            ],
            "diem": 19.0
        },
        {
            "THM": "B03",
            "mon": [
                "toan",
                "sinh",
                "van"
            ],
            "diem": 19.25
        },
        {
            "THM": "C02",
            "mon": [
                "van",
                "toan",
                "hoa"
            ],
            "diem": 22.5
        },
        {
            "THM": "C08",
            "mon": [
                "van",
                "hoa",
                "sinh"
            ],
            "diem": 24.0
        }
    ]
}