{
    "SBD": "49000015",
    "toan": 6.0,
    "van": 1.75,
    "ngoaiNgu": null,
    "su": null,
    "dia": 8.0,
    "GDKTPL": null,
    "li": null,
    "hoa": 2.75,
    "sinh": null,
    "tin": null,
    "congNghe": null,
    "maNgoaiNgu": null,
    "THMs": [
        {
            "THM": "A00",
            "mon": [
                "toan",
                "ly",
                "hoa"
            ],
            "diem": 10.5
        },
        {
            "THM": "A06",
            "mon": [
                "toan",
                "hoa",
                "dia"
            ],
            "diem": 16.75
        },
        {
            "THM": "C02",
            "mon": [
                "van",
                "toan",
                "hoa"
            ],
            "diem": 10.5
        },
        {
            "THM": "C04",
            "mon": [
                "van",
                "toan",
                "dia"
            ],
            "diem": 15.75
        }
    ]
}